mathstat_libpy/__init__.py
mathstat_libpy/pdf_.py
mathstat_libpy-1.3.0.dist-info/METADATA
mathstat_libpy-1.3.0.dist-info/WHEEL
mathstat_libpy-1.3.0.dist-info/top_level.txt
mathstat_libpy-1.3.0.dist-info/RECORD
